selenium_to_pdf/__init__.py
selenium_to_pdf/convert.py
selenium_to_pdf-0.3.0.dist-info/LICENSE
selenium_to_pdf-0.3.0.dist-info/WHEEL
selenium_to_pdf-0.3.0.dist-info/METADATA
selenium_to_pdf-0.3.0.dist-info/RECORD
